VHDL/exercicios_testench/two_comp/adder4.vhd
-------------------------------------------------------
--! @file adder4.vhd
--! @brief 4-bit carry lookahead adder
--! @author Edson S. Gomi (gomi@usp.br)
--! @date 2018-10-01
-------------------------------------------------------

library IEEE;
use IEEE.std_logic_1164.all;
use ieee.numeric_std.all;

entity adder4 is
  port (
        cin     :   in std_logic;
        x       :   in std_logic_vector (3 downto 0);
        y       :   in std_logic_vector (3 downto 0);
        sum     :   out std_logic_vector (3 downto 0);
        cout    :   out std_logic
    );
end entity adder4;

architecture adder4_arch of adder4 is

  signal g0,g1,g2,g3      :   std_logic;
  signal p0,p1,p2,p3      :   std_logic;
  signal c0,c1,c2,c3,c4   :   std_logic;
  signal x0,x1,x2,x3      :   std_logic;
  signal y0,y1,y2,y3      :   std_logic;
  
begin

  x0 <= x(0);
  x1 <= x(1);
  x2 <= x(2);
  x3 <= x(3);
  y0 <= y(0);
  y1 <= y(1);
  y2 <= y(2);
  y3 <= y(3);
  
  g0 <= x0  and  y0;
  p0 <= x0  xor  y0;
  g1 <= x1  and  y1;
  p1 <= x1  xor  y1;
  g2 <= x2  and  y2;
  p2 <= x2  xor  y2;
  g3 <= x3  and  y3;
  p3 <= x3  xor  y3;

  c0 <= cin;
  
  c1 <= g0 or (p0 and c0);
  c2 <= g1 or (p1 and g0) or (p1 and p0 and c0);
  c3 <= g2 or (p2 and g1) or (p2 and p1 and g0) or (p2 and p1 and p0 and c0);
  c4 <= g3 or (p3 and g2) or (p3 and p2 and g1) or (p3 and p2 and p1 and p0 and c0);

  cout <= c4;

  sum(0) <= x0 xor y0 xor c0;
  sum(1) <= x1 xor y1 xor c1;
  sum(2) <= x2 xor y2 xor c2;
  sum(3) <= x3 xor y3 xor c3;

end architecture adder4_arch;

VHDL/exercicios_testench/two_comp/adder4_tb.vhd
Library IEEE;
use IEEE.std_logic_1164.all;
use ieee.numeric_std.all;

entity adder4_tb is
end entity;

architecture testb of adder4_tb is

    component adder4 is
    port(
            cin     :   in std_logic;
            x       :   in std_logic_vector (3 downto 0);
            y       :   in std_logic_vector (3 downto 0);
            sum     :   out std_logic_vector (3 downto 0);
            cout    :   out std_logic
        );
    end component;

    signal a_in, b_in, s_out : std_logic_vector (3 downto 0);
    signal c_out : std_logic;

begin

    DUT: adder4 port map(
            cin => '0', 
            x => a_in, 
            y => b_in, 
            sum => s_out, 
            cout => c_out
        );

    process
    begin
        a_in <= "0000";
        b_in <= "0000";
        wait for 1 ns;
        assert(c_out & s_out = "00000") report "0+0 Falhou" severity error;

        a_in <= "0001";
        b_in <= "0001";
        wait for 1 ns;
        assert(c_out & s_out = "00010") report "1+1 Falhou" severity error;

        a_in <= "1000";
        b_in <= "1000";
        wait for 1 ns;
        assert(c_out & s_out = "10000") report "8+8 Falhou" severity error;

        a_in <= "1111";
        b_in <= "0001";
        wait for 1 ns;
        assert(c_out & s_out = "10000") report "F+1 Falhou" severity error;

        a_in <= "1110";
        b_in <= "0111";
        wait for 1 ns;
        assert(c_out & s_out = "10101") report "E+7 Falhou" severity error;

        a_in <= "0111";
        b_in <= "0011";
        wait for 1 ns;
        assert(c_out & s_out = "11010") report "7+3 Falhou" severity error;

        a_in <= "1100";
        b_in <= "0101";
        wait for 1 ns;
        assert(c_out & s_out = "10001") report "C+5 Falhou" severity error;

        a_in <= "0000";
        b_in <= "0000";

        assert false report "FIM DO TESTE." severity note;
        wait;
    end process;
end testb;

VHDL/exercicios_testench/two_comp/simul.vcd
$date
  Mon Sep  7 18:51:15 2020
$end
$version
  GHDL v0
$end
$timescale
  1 fs
$end
$scope module standard $end
$upscope $end
$scope module std_logic_1164 $end
$upscope $end
$scope module numeric_std $end
$upscope $end
$scope module adder4_tb $end
$var reg 4 ! a_in[3:0] $end
$var reg 4 " b_in[3:0] $end
$var reg 4 # s_out[3:0] $end
$var reg 1 $ c_out $end
$scope module dut $end
$var reg 1 % cin $end
$var reg 4 & x[3:0] $end
$var reg 4 ' y[3:0] $end
$var reg 4 ( sum[3:0] $end
$var reg 1 ) cout $end
$var reg 1 * g0 $end
$var reg 1 + g1 $end
$var reg 1 , g2 $end
$var reg 1 - g3 $end
$var reg 1 . p0 $end
$var reg 1 / p1 $end
$var reg 1 0 p2 $end
$var reg 1 1 p3 $end
$var reg 1 2 c0 $end
$var reg 1 3 c1 $end
$var reg 1 4 c2 $end
$var reg 1 5 c3 $end
$var reg 1 6 c4 $end
$var reg 1 7 x0 $end
$var reg 1 8 x1 $end
$var reg 1 9 x2 $end
$var reg 1 : x3 $end
$var reg 1 ; y0 $end
$var reg 1 < y1 $end
$var reg 1 = y2 $end
$var reg 1 > y3 $end
$upscope $end
$upscope $end
$enddefinitions $end
#0
b0000 !
b0000 "
b0000 #
0$
0%
b0000 &
b0000 '
b0000 (
0)
0*
0+
0,
0-
0.
0/
00
01
02
03
04
05
06
07
08
09
0:
0;
0<
0=
0>
#1000000
b0001 !
b0001 "
b0010 #
b0001 &
b0001 '
b0010 (
1*
13
17
1;
#2000000
b1000 !
b1000 "
b0000 #
1$
b1000 &
b1000 '
b0000 (
1)
0*
1-
03
16
07
1:
0;
1>
#3000000
b1111 !
b0001 "
b0000 #
0$
b1111 &
b0001 '
b0000 (
0)
1*
0-
1/
10
11
13
14
15
06
17
18
19
1;
0>
#4000000
b1110 !
b0111 "
b0101 #
1$
b1110 &
b0111 '
b0101 (
1)
0*
1+
1,
1.
0/
00
03
16
07
1<
1=
#5000000
b0111 !
b0011 "
b1010 #
0$
b0111 &
b0011 '
b1010 (
0)
1*
0,
0.
10
01
13
06
17
0:
0=
#6000000
b1100 !
b0101 "
b0001 #
1$
b1100 &
b0101 '
b0001 (
1)
0*
0+
1,
1.
00
11
03
04
16
07
08
1:
0<
1=
#7000000
b0000 !
b0000 "
b0000 #
0$
b0000 &
b0000 '
b0000 (
0)
0,
0.
01
05
06
09
0:
0;
0=
